pdf_to_markdown_summarizer/__init__.py
pdf_to_markdown_summarizer/cli.py
pdf_to_markdown_summarizer/config.py
pdf_to_markdown_summarizer/extractor.py
pdf_to_markdown_summarizer/summarizer.py
pdf_to_markdown_summarizer/utils.py
pdf_to_markdown_summarizer-0.1.0.dist-info/METADATA
pdf_to_markdown_summarizer-0.1.0.dist-info/WHEEL
pdf_to_markdown_summarizer-0.1.0.dist-info/entry_points.txt
pdf_to_markdown_summarizer-0.1.0.dist-info/licenses/LICENSE
pdf_to_markdown_summarizer-0.1.0.dist-info/RECORD
