Metadata-Version: 2.4
Name: pdf-to-markdown-summarizer
Version: 0.1.0
Summary: Summarizes PDF files into markdown format compendiums, assisted by AI.
Project-URL: Homepage, https://github.com/rezashahnazar/pdf-to-markdown-summarizer
Project-URL: Repository, https://github.com/rezashahnazar/pdf-to-markdown-summarizer
Project-URL: Issues, https://github.com/rezashahnazar/pdf-to-markdown-summarizer/issues
Author-email: Reza Shahnazar <reza.shahnazar@gmail.com>
License: MIT License
License-File: LICENSE
Keywords: ai,gemini,markdown,openai,pdf,summarizer
Classifier: Development Status :: 3 - Alpha
Classifier: Intended Audience :: Developers
Classifier: License :: OSI Approved :: MIT License
Classifier: Programming Language :: Python :: 3
Classifier: Programming Language :: Python :: 3.12
Classifier: Topic :: Software Development :: Libraries :: Python Modules
Classifier: Topic :: Text Processing :: Markup
Requires-Python: >=3.12
Requires-Dist: google-genai>=1.47.0
Requires-Dist: openai>=2.6.1
Requires-Dist: pydantic-settings>=2.11.0
Requires-Dist: pypdf[full]>=6.1.3
Requires-Dist: python-dotenv>=1.2.1
Provides-Extra: dev
Requires-Dist: black>=23.0.0; extra == 'dev'
Requires-Dist: pytest>=7.0.0; extra == 'dev'
Requires-Dist: ruff>=0.1.0; extra == 'dev'
